litdata/__about__.py
litdata/__init__.py
litdata/__main__.py
litdata/constants.py
litdata/debugger.py
litdata/helpers.py
litdata/imports.py
litdata/cli/__init__.py
litdata/cli/commands.py
litdata/cli/parser.py
litdata/processing/__init__.py
litdata/processing/data_processor.py
litdata/processing/functions.py
litdata/processing/readers.py
litdata/processing/utilities.py
litdata/raw/__init__.py
litdata/raw/dataset.py
litdata/raw/indexer.py
litdata/raw/types.py
litdata/streaming/__init__.py
litdata/streaming/cache.py
litdata/streaming/client.py
litdata/streaming/combined.py
litdata/streaming/compression.py
litdata/streaming/config.py
litdata/streaming/dataloader.py
litdata/streaming/dataset.py
litdata/streaming/downloader.py
litdata/streaming/fs_provider.py
litdata/streaming/item_loader.py
litdata/streaming/parallel.py
litdata/streaming/reader.py
litdata/streaming/resolver.py
litdata/streaming/sampler.py
litdata/streaming/serializers.py
litdata/streaming/shuffle.py
litdata/streaming/writer.py
litdata/utilities/__init__.py
litdata/utilities/_pytree.py
litdata/utilities/base.py
litdata/utilities/breakpoint.py
litdata/utilities/broadcast.py
litdata/utilities/dataset_utilities.py
litdata/utilities/encryption.py
litdata/utilities/env.py
litdata/utilities/format.py
litdata/utilities/hf_dataset.py
litdata/utilities/packing.py
litdata/utilities/parquet.py
litdata/utilities/shuffle.py
litdata/utilities/subsample.py
litdata/utilities/torch_utils.py
litdata/utilities/train_test_split.py
litdata-0.2.59.dist-info/licenses/LICENSE
litdata-0.2.59.dist-info/METADATA
litdata-0.2.59.dist-info/WHEEL
litdata-0.2.59.dist-info/entry_points.txt
litdata-0.2.59.dist-info/top_level.txt
litdata-0.2.59.dist-info/RECORD
