Metadata-Version: 2.4
Name: litdata
Version: 0.2.59
Summary: The Deep Learning framework to train, deploy, and ship AI products Lightning fast.
Home-page: https://github.com/Lightning-AI/litdata
Download-URL: https://github.com/Lightning-AI/litdata
Author: Lightning AI et al.
Author-email: pytorch@lightning.ai
License: Apache-2.0
Project-URL: Bug Tracker, https://github.com/Lightning-AI/litdata/issues
Project-URL: Documentation, https://lightning-ai.github.io/litdata/
Project-URL: Source Code, https://github.com/Lightning-AI/litdata
Keywords: deep learning,pytorch,AI,streaming,cloud,data processing
Classifier: Environment :: Console
Classifier: Natural Language :: English
Classifier: Development Status :: 4 - Beta
Classifier: Intended Audience :: Developers
Classifier: Topic :: Scientific/Engineering :: Artificial Intelligence
Classifier: Topic :: Scientific/Engineering :: Information Analysis
Classifier: Operating System :: OS Independent
Classifier: Programming Language :: Python :: 3
Classifier: Programming Language :: Python :: 3.10
Classifier: Programming Language :: Python :: 3.11
Classifier: Programming Language :: Python :: 3.12
Classifier: Programming Language :: Python :: 3.13
Classifier: Programming Language :: Python :: 3.14
Requires-Python: >=3.10
License-File: LICENSE
Requires-Dist: torch
Requires-Dist: torchvision
Requires-Dist: lightning-utilities
Requires-Dist: filelock
Requires-Dist: numpy
Requires-Dist: boto3
Requires-Dist: requests
Requires-Dist: tifffile
Requires-Dist: obstore
Dynamic: author
Dynamic: author-email
Dynamic: classifier
Dynamic: description
Dynamic: description-content-type
Dynamic: download-url
Dynamic: home-page
Dynamic: keywords
Dynamic: license
Dynamic: license-file
Dynamic: project-url
Dynamic: requires-dist
Dynamic: requires-python
Dynamic: summary
